tec/__init__.py
tec/dependencies.py
tec/doctest_utils.py
tec/findimports.py
tec/import_counting.py
tec/misc.py
tec/modules.py
tec/packages.py
tec/peek.py
tec/pip_packaging.py
tec/pip_requirements.py
tec/snake_food_import_counting.py
tec/stores.py
tec/util.py
tec/examples/__init__.py
tec/misc/__init__.py
tec/misc/manage_pth_file.py
tec-0.0.17.dist-info/LICENSE
tec-0.0.17.dist-info/METADATA
tec-0.0.17.dist-info/WHEEL
tec-0.0.17.dist-info/top_level.txt
tec-0.0.17.dist-info/RECORD
