Metadata-Version: 2.1
Name: tec
Version: 0.0.17
Summary: Tools to inspect python objects
Home-page: https://github.com/thorwhalen/tec
Author: Thor Whalen
License: apache-2.0
Platform: any
License-File: LICENSE
Requires-Dist: dol
Requires-Dist: xdol
Requires-Dist: pandas
Requires-Dist: cchardet
